[
  {
    "id": 1,
    "name": "KÖFTE ",
    "removeCart": "AKTİF SİPARİŞ"
  },
  {
    "id": 2,
    "name": " KÖFTE",
    "removeCart": "AKTİF SİPARİŞ"

  },
  {
    "id": 3,
    "name": "KÖFTE",
    "removeCart": "AKTİF SİPARİŞ"

  },
  {
    "id": 4,
    "name": " KÖFTE",
    "removeCart": "AKTİF SİPARİŞ"

  },
  {
    "id": 5,
    "name": " KÖFTE",
    "removeCart": "AKTİF SİPARİŞ"

  },
  {
    "id": 6,
    "name": " KÖFTE",
    "removeCart": "AKTİF SİPARİŞ"

  },
  {
    "id": 7,
    "name": "KÖFTE",
    "removeCart": "AKTİF SİPARİŞ"

  },
  {
    "id": 8,
    "name": "KÖFTE",
    "removeCart": "AKTİF SİPARİŞ"

  }
]
